dihi_datavault/__init__.py
dihi_datavault/cli.py
dihi_datavault-0.1.0.dist-info/entry_points.txt
dihi_datavault-0.1.0.dist-info/LICENSE.txt
dihi_datavault-0.1.0.dist-info/WHEEL
dihi_datavault-0.1.0.dist-info/METADATA
dihi_datavault-0.1.0.dist-info/RECORD
