Metadata-Version: 2.1
Name: dihi-datavault
Version: 0.1.0
Summary: Store and encrypt sensitive data in your git repo
Home-page: https://github.com/dihi/datavault
License: Proprietary
Author: Faraz Yashar
Author-email: fny@duke.edu
Requires-Python: >=3.7.2
Classifier: License :: Other/Proprietary License
Classifier: Programming Language :: Python :: 3
Classifier: Programming Language :: Python :: 3.10
Classifier: Programming Language :: Python :: 3.8
Classifier: Programming Language :: Python :: 3.9
Requires-Dist: click (>=8.1.3,<9.0.0)
Requires-Dist: colorama (>=0.4.5,<0.5.0)
Requires-Dist: cryptography (>=37.0.4,<38.0.0)
